flati/__init__.py
flati/__init__.pyi
flati/py.typed
flati/py2.py
flati/py3.py
flati/py3.pyi
flati-0.2.1.data/data/CHANGES.rst
flati-0.2.1.data/data/README.rst
flati-0.2.1.dist-info/licenses/LICENSE
flati-0.2.1.dist-info/METADATA
flati-0.2.1.dist-info/WHEEL
flati-0.2.1.dist-info/top_level.txt
flati-0.2.1.dist-info/RECORD
